MANIFEST.in
README.rst
setup.cfg
setup.py
bin/pfioh
pfioh/__init__.py
pfioh/mount_dir.py
pfioh/pfioh.py
pfioh/swift_store.py
pfioh.egg-info/PKG-INFO
pfioh.egg-info/SOURCES.txt
pfioh.egg-info/dependency_links.txt
pfioh.egg-info/not-zip-safe
pfioh.egg-info/requires.txt
pfioh.egg-info/top_level.txt