Metadata-Version: 1.0
Name: pfioh
Version: 1.6.0.2
Summary: Path-and-File-IO-over-HTTP
Home-page: https://github.com/FNNDSC/pfioh
Author: Rudolph Pienaar
Author-email: rudolph.pienaar@gmail.com
License: MIT
Platform: UNKNOWN
